data_recon/__init__.py
data_recon/config.py
data_recon/database.py
data_recon/main.py
data_recon/connectors/__init__.py
data_recon/connectors/base.py
data_recon/connectors/mysql_connector.py
data_recon/connectors/snowflake_connector.py
data_recon/models/__init__.py
data_recon/models/datasource.py
data_recon/models/job.py
data_recon/routers/__init__.py
data_recon/routers/datasources.py
data_recon/routers/jobs.py
data_recon/schemas/__init__.py
data_recon/schemas/datasource.py
data_recon/schemas/job.py
data_recon/services/__init__.py
data_recon/services/datasource_service.py
data_recon/services/job_service.py
data_recon/services/recon_service.py
mcp_server/__init__.py
mcp_server/__main__.py
mcp_server/server.py
mcp_server/tools.py
data_recon_mcp-0.2.0.dist-info/METADATA
data_recon_mcp-0.2.0.dist-info/WHEEL
data_recon_mcp-0.2.0.dist-info/entry_points.txt
data_recon_mcp-0.2.0.dist-info/top_level.txt
data_recon_mcp-0.2.0.dist-info/RECORD
