Metadata-Version: 2.4
Name: data-recon-mcp
Version: 0.2.0
Summary: MCP Server for Data Reconciliation between MySQL and Snowflake
Author: Raj Hindocha
License: MIT
Project-URL: Homepage, https://github.com/hindocharaj1997/data-recon-mcp
Project-URL: Documentation, https://github.com/hindocharaj1997/data-recon-mcp#readme
Project-URL: Repository, https://github.com/hindocharaj1997/data-recon-mcp
Project-URL: Issues, https://github.com/hindocharaj1997/data-recon-mcp/issues
Keywords: mcp,data-reconciliation,mysql,snowflake,llm,claude,antigravity
Classifier: Development Status :: 3 - Alpha
Classifier: Intended Audience :: Developers
Classifier: License :: OSI Approved :: MIT License
Classifier: Programming Language :: Python :: 3
Classifier: Programming Language :: Python :: 3.10
Classifier: Programming Language :: Python :: 3.11
Classifier: Programming Language :: Python :: 3.12
Classifier: Topic :: Database
Classifier: Topic :: Software Development :: Libraries :: Python Modules
Requires-Python: >=3.10
Requires-Dist: fastapi>=0.109.0
Requires-Dist: uvicorn>=0.27.0
Requires-Dist: sqlalchemy>=2.0.0
Requires-Dist: pydantic>=2.0.0
Requires-Dist: pydantic-settings>=2.0.0
Requires-Dist: pymysql>=1.1.0
Requires-Dist: snowflake-connector-python>=3.6.0
Requires-Dist: mcp>=1.0.0
Requires-Dist: httpx>=0.26.0
Provides-Extra: dev
Requires-Dist: pytest>=8.0.0; extra == "dev"
Requires-Dist: pytest-asyncio>=0.23.0; extra == "dev"
